{"byteGate":{"internal":{"cn":"https://bytegate-sg.byteintlapi.com","i18n":"https://bytegate-sg.byteintlapi.com"},"tob":{"cn":"https://bytegate-sg.byteintlapi.com","i18n":"https://bytegate-sg.byteintlapi.com"}},"tea":{"verifyUrlCN":"https://mcs.byteoversea.net","verifyUrlI18n":"https://mcs.byteoversea.net","abServiceInternal":{"cn":"https://libraweb-va.tiktok.com","us":"https://libraweb-va.tiktok.com","sg":"https://libraweb-va.tiktok.com"},"abServiceExternal":{"cn":"https://libraweb-va.tiktok.com","us":"https://libraweb-va.tiktok.com","sg":"https://libraweb-va.tiktok.com"}},"slardarPC":{"cn":"https://pc-mon-sg.byteintlapi.com","i18n":"https://pc-mon-sg.byteintlapi.com"},"deviceRegister":{"cn":"https://log.byteoversea.com","i18n":"https://log.byteoversea.com"},"copilotDomain":{"cn":"https://copilot.byteintl.net","us":"https://copilot.byteintl.net","usog":"https://copilot-og.byteintl.net","sg":"https://copilot-sg.byteintl.net","sgog":"https://copilot-sg-og.byteintl.net","boe":"https://copilot-sg.byteintl.net"},"mcpPlugin":{"innerExtensionGallery":{"server":{"cn":"","sg":"","us":""},"client":{"cn":"ide-market-us.tiktok-row.net","sg":"ide-market-us.tiktok-row.net","us":"ide-market-us.tiktok-row.net"}},"outerExtensionGallery":{"server":{"cn":"api.trae.ai","sg":"api.trae.ai","us":"api.trae.ai"},"client":{"cn":"api.trae.ai","sg":"api.trae.ai","us":"api.trae.ai"}},"innerAgentExtensionGalleryBase":"api.trae.ai","outerNewExtensionGalleryBase":"api.trae.ai"},"appProviderLogin":{"marscode":{"boe":{"sg":{"apiUrl":"api.marscode.com","authUrl":"www.marscode.com"},"us":{"apiUrl":"api.marscode.com","authUrl":"www.marscode.com"},"cn":{"apiUrl":"api.marscode.com","authUrl":"www.marscode.com"}},"ppe":{"sg":{"apiUrl":"api.marscode.com","authUrl":"www.marscode.com"},"us":{"apiUrl":"api.marscode.com","authUrl":"www.marscode.com"},"cn":{"apiUrl":"api.marscode.com","authUrl":"www.marscode.com"}},"prod":{"sg":{"apiUrl":"api.marscode.com","authUrl":"www.marscode.com"},"us":{"apiUrl":"api.marscode.com","authUrl":"www.marscode.com"},"cn":{"apiUrl":"api.marscode.com","authUrl":"www.marscode.com"}},"prodog":{"sg":{"apiUrl":"api.marscode.com","authUrl":"www.marscode.com"},"us":{"apiUrl":"api.marscode.com","authUrl":"www.marscode.com"},"cn":{"apiUrl":"api.marscode.com","authUrl":"www.marscode.com"}}},"saas":{"boe":{"cn":{"authUrl":"","apiUrl":"api.enterprise.mcdemo.show"},"sg":{"authUrl":"","apiUrl":"api.enterprise.mcdemo.show"},"us":{"authUrl":"","apiUrl":"api.enterprise.mcdemo.show"}},"ppe":{"cn":{"authUrl":"","apiUrl":"api.enterprise.mcdemo.show"},"sg":{"authUrl":"","apiUrl":"api.enterprise.mcdemo.show"},"us":{"authUrl":"","apiUrl":"api.enterprise.mcdemo.show"}},"prod":{"cn":{"authUrl":"","apiUrl":"api.enterprise.mcdemo.show"},"sg":{"authUrl":"","apiUrl":"api.enterprise.mcdemo.show"},"us":{"authUrl":"","apiUrl":"api.enterprise.mcdemo.show"}},"prodog":{"cn":{"authUrl":"","apiUrl":"api.enterprise.mcdemo.show"},"sg":{"authUrl":"","apiUrl":"api.enterprise.mcdemo.show"},"us":{"authUrl":"","apiUrl":"api.enterprise.mcdemo.show"}}}},"bannerInfo":{"externalDomainListCN":[],"internalDomainListCN":[]},"CubeIDELogin":"","ChatverseHost":{"cn":"","us":"https://chatverse-us.byteintl.net","i18n":"https://chatverse.byteintl.net","usProd":"https://chatverse-us-prod.byteintl.net","i18nProd":"https://chatverse-prod.byteintl.net"},"ttnet":{"cn":{"domainHttpdns":"34.102.215.99","domainNetlog":"ttnet-sg.byteoversea.com","tncHostFirst":"tnc16-alisg.isnssdk.com"},"i18n":{"domainHttpdns":"34.102.215.99","domainNetlog":"ttnet-sg.byteoversea.com","tncHostFirst":"tnc16-alisg.isnssdk.com"}},"INTERNAL_USER_GROUP":"","TRAE_AI_HOME_PAGE":"","USER_GROUP":{"INTERNAL_USER_GROUP":"","TOB_USER_GROUP_CN":"","TOB_USER_GROUP_OVERSEA":"https://www.marscode.com","INTERNAL_MANUAL_DOC":"","APPLY_GUIDANCE_INTERNAL_USER_MANUAL":"","TOB_MANUAL_DOC_CN":"","TOB_MANUAL_DOC_OVERSEA":"https://docs.marscode.com"},"TRAE_THEME_SCOPE":"","SaasServer":{"boeCopilot":{"cn":"","sg":"","us":""},"ppeCopilot":{"cn":"","sg":"","us":""},"prodCopilot":{"cn":"","sg":"","us":""}},"externalCopilotDomains":{"usex":"https://a0ai-api.byteintlapi.com","cnex":"https://a0ai-api.byteintlapi.com","boe":"https://a0ai-api.byteintlapi.com"},"modelSelectIconHost":"","DataFinderChannelDomain":"","mcpDebugUrl":"","keywordSearchDownloadURLPrefix":"","keywordSearchDownloadURLPrefixTos":"","mcp_stdio_puppeteer_avatar_url_host":"","SAAS_ISSUE_REPORT_CN":"","config":{"ttnetParams":{"domainHttpdns":"","domainNetlog":"","tncHostFirst":""}}}
